stig/__init__.py
stig/__main__.py
stig/cliopts.py
stig/helpmgr.py
stig/hooks.py
stig/logging.py
stig/main.py
stig/objects.py
stig/client/__init__.py
stig/client/api.py
stig/client/base.py
stig/client/constants.py
stig/client/errors.py
stig/client/poll.py
stig/client/rdns.py
stig/client/trequestpool.py
stig/client/ttypes.py
stig/client/utils.py
stig/client/aiotransmission/__init__.py
stig/client/aiotransmission/api_freespace.py
stig/client/aiotransmission/api_settings.py
stig/client/aiotransmission/api_status.py
stig/client/aiotransmission/api_torrent.py
stig/client/aiotransmission/rpc.py
stig/client/aiotransmission/torrent.py
stig/client/filters/__init__.py
stig/client/filters/base.py
stig/client/filters/file.py
stig/client/filters/peer.py
stig/client/filters/setting.py
stig/client/filters/torrent.py
stig/client/filters/tracker.py
stig/client/filters/utils.py
stig/client/sorters/__init__.py
stig/client/sorters/base.py
stig/client/sorters/peer.py
stig/client/sorters/setting.py
stig/client/sorters/torrent.py
stig/client/sorters/tracker.py
stig/commands/__init__.py
stig/commands/cmdbase.py
stig/commands/cmderror.py
stig/commands/cmdmanager.py
stig/commands/guess_ui.py
stig/commands/utils.py
stig/commands/base/__init__.py
stig/commands/base/_common.py
stig/commands/base/_mixin.py
stig/commands/base/config.py
stig/commands/base/file.py
stig/commands/base/misc.py
stig/commands/base/peer.py
stig/commands/base/torrent.py
stig/commands/base/tracker.py
stig/commands/cli/__init__.py
stig/commands/cli/_common.py
stig/commands/cli/_mixin.py
stig/commands/cli/_table.py
stig/commands/cli/config.py
stig/commands/cli/file.py
stig/commands/cli/misc.py
stig/commands/cli/peer.py
stig/commands/cli/torrent.py
stig/commands/cli/tracker.py
stig/commands/tui/__init__.py
stig/commands/tui/_common.py
stig/commands/tui/_mixin.py
stig/commands/tui/config.py
stig/commands/tui/file.py
stig/commands/tui/misc.py
stig/commands/tui/peer.py
stig/commands/tui/torrent.py
stig/commands/tui/tracker.py
stig-0.14.2a0.dist-info/licenses/LICENSE
stig-0.14.2a0.dist-info/METADATA
stig-0.14.2a0.dist-info/WHEEL
stig-0.14.2a0.dist-info/entry_points.txt
stig-0.14.2a0.dist-info/top_level.txt
stig-0.14.2a0.dist-info/RECORD
